pr_streamlit_template/__init__.py
pr_streamlit_template/assets/css/streamlit_PR.css
pr_streamlit_template/assets/images/background_image.png
pr_streamlit_template/assets/images/logo_coe.png
pr_streamlit_template/assets/images/logo_global_data.png
pr_streamlit_template-0.3.0.dist-info/LICENSE
pr_streamlit_template-0.3.0.dist-info/WHEEL
pr_streamlit_template-0.3.0.dist-info/METADATA
pr_streamlit_template-0.3.0.dist-info/RECORD
