Metadata-Version: 2.1
Name: pr-streamlit-template
Version: 0.3.0
Summary: A PR streamlit template
Home-page: https://github.com/gamcoh/pr-streamlit-template
License: MIT
Keywords: Pernod Ricard,PR,Data,Global Data,Data COE
Author: gamcoh
Author-email: cohengamliel8@gmail.com
Requires-Python: >=3.8,<4.0
Classifier: Development Status :: 3 - Alpha
Classifier: Intended Audience :: Developers
Classifier: License :: OSI Approved :: MIT License
Classifier: Operating System :: OS Independent
Classifier: Programming Language :: Python :: 3
Classifier: Programming Language :: Python :: 3.8
Classifier: Programming Language :: Python :: 3.9
Classifier: Programming Language :: Python :: 3.10
Classifier: Programming Language :: Python :: 3
Classifier: Programming Language :: Python :: 3.8
Classifier: Programming Language :: Python :: 3.9
Classifier: Topic :: Software Development :: Libraries :: Python Modules
Requires-Dist: streamlit (>=1.19.0,<2.0.0)
Project-URL: Repository, https://github.com/gamcoh/pr-streamlit-template
